AUTHORS
CHANGELOG
INSTALL
LICENSE
MANIFEST.in
README.rst
VERSION
setup.cfg
setup.py
djangoplicity_python_avm_library.egg-info/PKG-INFO
djangoplicity_python_avm_library.egg-info/SOURCES.txt
djangoplicity_python_avm_library.egg-info/dependency_links.txt
djangoplicity_python_avm_library.egg-info/top_level.txt
docs/html/.buildinfo
docs/html/appendix.html
docs/html/developers.html
docs/html/genindex.html
docs/html/index.html
docs/html/installation.html
docs/html/introduction.html
docs/html/objects.inv
docs/html/py-modindex.html
docs/html/reference.html
docs/html/search.html
docs/html/searchindex.js
docs/html/using.html
docs/html/_sources/appendix.txt
docs/html/_sources/developers.txt
docs/html/_sources/index.txt
docs/html/_sources/installation.txt
docs/html/_sources/introduction.txt
docs/html/_sources/reference.txt
docs/html/_sources/using.txt
docs/html/_static/basic.css
docs/html/_static/default.css
docs/html/_static/doctools.js
docs/html/_static/file.png
docs/html/_static/jquery.js
docs/html/_static/minus.png
docs/html/_static/plus.png
docs/html/_static/pygments.css
docs/html/_static/searchtools.js
docs/html/_static/sidebar.js
docs/html/_static/underscore.js
libavm/__init__.py
libavm/core.py
libavm/cv.py
libavm/datatypes.py
libavm/exceptions.py
libavm/specs.py
libavm/utils.py
test/samples.py
test/test_core.py
test/test_datatypes.py
test/test_utils.py