Metadata-Version: 2.1
Name: djangoplicity-python-avm-library
Version: 1.0.3
Summary: Python AVM Library for working with Astronomy Visualization Metadata.
Home-page: https://github.com/djangoplicity/djangoplicity-python-avm-library
Download-URL: https://github.com/djangoplicity/djangoplicity-python-avm-library/archive/refs/tags/1.0.3.tar.gz
Author: Amit Kapadia
Author-email: akapad@gmail.com
License: New BSD License
License-File: LICENSE
License-File: AUTHORS
